[
    {
        "id":"1",
        "img":"http://b1-q.mafengwo.net/s16/M00/89/31/CoUBUl6VW2WALqr1AAFuFHIwu6k72.jpeg?imageMogr2%2Fthumbnail%2F%21220x150r%2Fstrip%2Fgravity%2FCenter%2Fcrop%2F%21220x150%2Fquality%2F90",
        "title":"上帝的眼泪，锡兰微笑，这是我不能忘记的斯里兰卡（13天行程...",
        "content":" 第六天，努沃埃利耶，从茶厂到粉红邮局 洛奇奇茶厂，兰卡最受欢迎的茶厂 对于喜欢喝茶的人来说， 斯里兰卡 的红茶可是一个很大的诱惑，谁都知道，锡兰红茶世界闻名，谁都想亲口品尝一下。所...",
        "city":"斯里兰卡",
        "head":"http://b1-q.mafengwo.net/s15/M00/6D/84/CoUBGV4n7YOAG2LwAABHT5LFfp020.jpeg?imageMogr2%2Fthumbnail%2F%2116x16r%2Fgravity%2FCenter%2Fcrop%2F%2116x16%2Fquality%2F90",
        "name":"郝地瓜Cynthia",
        "num":"6305/28",
        "bing":"260",
        "app":"0"
    },
    {
        "id":"2",
        "img":"http://b1-q.mafengwo.net/s16/M00/82/A3/CoUBUl6Ss6iAO5WDADf42CBjLpg411.jpg?imageMogr2%2Fthumbnail%2F%21220x150r%2Fstrip%2Fgravity%2FCenter%2Fcrop%2F%21220x150%2Fquality%2F90",
        "title":"在花海中探寻两汉三国历史丨汉中春季赏花自驾游记(附最美拍照...",
        "content":" 春天的汉中，是花海的世界 春天的 汉中 ，是花海的世界， 当春风来临，大地开始了新一轮的苏醒。 仿佛所有的 花都 在同一时间沸腾了起来， 山边梯田里的油菜花、樱桃沟里的樱桃花、天荡山谷...",
        "city":"汉中",
        "head":"http://n1-q.mafengwo.net/s12/M00/01/26/wKgED1xFofyAD09oAArunqAUCH808.jpeg?imageMogr2%2Fthumbnail%2F%2116x16r%2Fgravity%2FCenter%2Fcrop%2F%2116x16%2Fquality%2F90",
        "name":"梦游前生",
        "num":"9950/49",
        "bing":"426",
        "app":"1"
    },
    {
        "id":"3",
        "img":"http://b1-q.mafengwo.net/s16/M00/C5/E7/CoUBUl6cvWmAcddiAAeUydTNRkc669.jpg?imageMogr2%2Fthumbnail%2F%21220x150r%2Fstrip%2Fgravity%2FCenter%2Fcrop%2F%21220x150%2Fquality%2F90",
        "title":"日本·北海道 | 十二月的初冬，赴一场暖阳下的皑皑白雪",
        "content":"又是暖冬，未见雪飘。 对于生活在南方的我们，亲眼目睹这个世界变得银装素裹，雪，盖满了屋顶，空中，晶莹的雪花慢慢飘落。 这一切仿佛只是一场奢望。 别人说，冷，是因为听见了下雪的声音。...",
        "city":"北海道",
        "head":"http://n1-q.mafengwo.net/s9/M00/1E/4F/wKgBs1ZgavqAQZK0AABYAtXMbAM52.jpeg?imageMogr2%2Fthumbnail%2F%2116x16r%2Fgravity%2FCenter%2Fcrop%2F%2116x16%2Fquality%2F90",
        "name":"阳光男该张小凡",
        "num":"7498/42",
        "bing":"297",
        "app":"1"
    },
    {
        "id":"4",
        "img":"http://n1-q.mafengwo.net/s16/M00/E8/14/CoUBUl6WiCaAVgxrAAsQkW5HW1w859.jpg?imageMogr2%2Fthumbnail%2F%21220x150r%2Fstrip%2Fgravity%2FCenter%2Fcrop%2F%21220x150%2Fquality%2F90",
        "title":"消失的地平线上的“香巴拉”和“女儿国”——秋游香格里拉、...",
        "content":"在《消失的地平线》里，描绘了一个隐藏在 中国 西南部的净土乐园——那是一个充满祥和、宁静、永恒和神秘色彩的藏族生息之地。在那里，三条河流交汇在一起，群山高耸入云，山顶白雪皑皑，脚...",
        "city":"香格里拉",
        "head":"http://n1-q.mafengwo.net/s7/M00/20/44/wKgB6lP7Iv-AICZKAAEIh2Copbc10.jpeg?imageMogr2%2Fthumbnail%2F%2116x16r%2Fgravity%2FCenter%2Fcrop%2F%2116x16%2Fquality%2F90",
        "name":"Jerry",
        "num":" 9644/86",
        "bing":"520",
        "app":"0"
    },
    {
        "id":"5",
        "img":"http://n1-q.mafengwo.net/s16/M00/CB/4F/CoUBUl6ItrKAd1b5ABnBmFWkEXA194.JPG?imageMogr2%2Fthumbnail%2F%21220x150r%2Fstrip%2Fgravity%2FCenter%2Fcrop%2F%21220x150%2Fquality%2F90",
        "title":"花见三城：京都、奈良、名古屋的26处樱花印象",
        "content":"三分至满开，留下樱吹雪的残念 很久之前便听闻 日本 关西 樱花的盛名，是“一生必赏一次的绝景”。 于是在清明时节，我来到 日本 关西 。八天时间，在 名古屋 、 京都 、 奈良 三城间辗转往...",
        "city":"京都",
        "head":"http://b1-q.mafengwo.net/s13/M00/09/AD/wKgEaVy3ziiAZkmFAACxxUhWHsc44.jpeg?imageMogr2%2Fthumbnail%2F%2116x16r%2Fgravity%2FCenter%2Fcrop%2F%2116x16%2Fquality%2F90",
        "name":"sockmai",
        "num":" 6076/29",
        "bing":"2349",
        "app":"0"
    },
    {
        "id":"6",
        "img":"http://n1-q.mafengwo.net/s16/M00/E4/E9/CoUBUl6Yc2uAZn57AA0qLpq18N8333.jpg?imageMogr2%2Fthumbnail%2F%21220x150r%2Fstrip%2Fgravity%2FCenter%2Fcrop%2F%21220x150%2Fquality%2F90",
        "title":"盛夏七月，一次中东之约,一场应许之旅",
        "content":"前言 以色列 和 约旦 ， 中东 文化中的明珠，历史文明古国、宗教圣地，没有太多的犹豫，今年的旅行地图锁定在了 中东 准备这一场旅行真的耗费了我大量的日日夜夜，为了行程、为了住宿、为了...",
        "city":"以色列",
        "head":"http://p1-q.mafengwo.net/s16/M00/57/2F/CoUBUl6jvBmAL00tABhW48I5aEY74.jpeg?imageMogr2%2Fthumbnail%2F%2116x16r%2Fgravity%2FCenter%2Fcrop%2F%2116x16%2Fquality%2F90",
        "name":"大香芋",
        "num":" 6543/62",
        "bing":"349",
        "app":"0"
    },
    {
        "id":"7",
        "img":"http://b1-q.mafengwo.net/s16/M00/89/31/CoUBUl6VW2WALqr1AAFuFHIwu6k72.jpeg?imageMogr2%2Fthumbnail%2F%21220x150r%2Fstrip%2Fgravity%2FCenter%2Fcrop%2F%21220x150%2Fquality%2F90",
        "title":"上帝的眼泪，锡兰微笑，这是我不能忘记的斯里兰卡（13天行程...",
        "content":"第六天，努沃埃利耶，从茶厂到粉红邮局 洛奇奇茶厂，兰卡最受欢迎的茶厂 对于喜欢喝茶的人来说， 斯里兰卡 的红茶可是一个很大的诱惑，谁都知道，锡兰红茶世界闻名，谁都想亲口品尝一下。所...",
        "city":"斯里兰卡",
        "head":"http://b1-q.mafengwo.net/s15/M00/6D/84/CoUBGV4n7YOAG2LwAABHT5LFfp020.jpeg?imageMogr2%2Fthumbnail%2F%2116x16r%2Fgravity%2FCenter%2Fcrop%2F%2116x16%2Fquality%2F90",
        "name":" 郝地瓜Cynthia",
        "num":"5675/24",
        "bing":"234",
        "app":"0"
    },
    {
        "id":"8",
        "img":"http://p1-q.mafengwo.net/s16/M00/08/B4/CoUBUl6VcYCAUwTTAAwMaS--fKc18.jpeg?imageMogr2%2Fthumbnail%2F%21220x150r%2Fstrip%2Fgravity%2FCenter%2Fcrop%2F%21220x150%2Fquality%2F90",
        "title":"日本漫游Day5 | 教练我想去镰仓",
        "content":"湘南海岸边的小城 说起 镰仓 ，你会想起什么呢？许多爱看动漫的年青人对 镰仓 的最初了解，应该来自于《灌篮高手》中的那经典一幕：海边的 镰仓 高校前站。对于陶醉在《 镰仓 物语》那文艺...",
        "city":"镰仓",
        "head":"http://n1-q.mafengwo.net/s15/M00/C3/12/CoUBGV4M8EWAU9RLAAC3ZLKaH8E32.jpeg?imageMogr2%2Fthumbnail%2F%2116x16r%2Fgravity%2FCenter%2Fcrop%2F%2116x16%2Fquality%2F90",
        "name":"行者",
        "num":"5856/20",
        "bing":"220",
        "app":"0"
    },
    {
        "id":"9",
        "img":"http://b1-q.mafengwo.net/s16/M00/DB/98/CoUBUl6NsEaAD8pFAAxZ3lQ5K1k547.jpg?imageMogr2%2Fthumbnail%2F%21220x150r%2Fstrip%2Fgravity%2FCenter%2Fcrop%2F%21220x150%2Fquality%2F90",
        "title":"#不止于春#去齐鲁，还一场春债（山东济南/济宁/泰安/聊城/日...",
        "content":"你说 胭脂用尽时，桃花就开了。 如今 夭桃满山谷，春风渡齐鲁。 于这孔孟之乡、礼仪之邦， 种下惠风和煦，栽下杏雨梨云。 从此 翠袖围香，绛绡落雪，芳息入骨， 惹来一身偿还不掉的春债。 济...",
        "city":"泰安",
        "head":"http://b1-q.mafengwo.net/s15/M00/E7/0F/CoUBGV4FlPmABPcpAABNJgFDHVI66.jpeg?imageMogr2%2Fthumbnail%2F%2116x16r%2Fgravity%2FCenter%2Fcrop%2F%2116x16%2Fquality%2F90",
        "name":"Drizzle细雨",
        "num":"9824/68",
        "bing":"515",
        "app":"0"
    },
    {
        "id":"10",
        "img":"http://p1-q.mafengwo.net/s16/M00/1C/5F/CoUBUl6K6kCAGWTlAAtskdwHOlM966.jpg?imageMogr2%2Fthumbnail%2F%21220x150r%2Fstrip%2Fgravity%2FCenter%2Fcrop%2F%21220x150%2Fquality%2F90",
        "title":"【东京—镰仓—高松—小豆岛—直岛—丰岛】东京的大雨，镰仓...",
        "content":"“快乐啊， 有时候不是大笑， 不是跟你笑着拥抱， 而是你看着他， 他看着你， 然后你们不知不觉的就笑了” 写在开篇 第三次去 日本 ，在 东京 和高松、 东京 和 屋久岛 的行程中犹豫了很久...",
        "city":"日本",
        "head":"http://b1-q.mafengwo.net/s16/M00/20/09/CoUBUl6K7V6AYpEqAAEE0xAOP6E52.jpeg?imageMogr2%2Fthumbnail%2F%2116x16r%2Fgravity%2FCenter%2Fcrop%2F%2116x16%2Fquality%2F90",
        "name":"嘉errr",
        "num":"9860/19",
        "bing":"340",
        "app":"0"
    },
    {
        "id":"11",
        "img":"http://p1-q.mafengwo.net/s16/M00/D4/B4/CoUBUl6YZrCAbtPNAA2aYXj0vc4603.jpg?imageMogr2%2Fthumbnail%2F%21220x150r%2Fstrip%2Fgravity%2FCenter%2Fcrop%2F%21220x150%2Fquality%2F90",
        "title":"一篇迟到五年的游记 | 台湾环岛八日全记录",
        "content":"intro 说起 台湾 最初的记忆是小时候听到的那些流行歌曲 某某歌星是 台湾 的 小时候只知道 台湾 这么一个地方 因为以前条件限制 获取资讯只能通过电视 或者音乐影视这些媒介 对 台湾 的了解...",
        "city":"台湾",
        "head":"http://b1-q.mafengwo.net/s10/M00/4C/FC/wKgBZ1j1y-SACwgKAAFX3v7cyoA06.jpeg?imageMogr2%2Fthumbnail%2F%2116x16r%2Fgravity%2FCenter%2Fcrop%2F%2116x16%2Fquality%2F90",
        "name":"1983",
        "num":" 3762/5",
        "bing":"264",
        "app":"0"
    },
    {
        "id":"12",
        "img":"http://p1-q.mafengwo.net/s16/M00/67/A8/CoUBUl75lq-AVGLvAAhscFRnKwM636.jpg?imageMogr2%2Fthumbnail%2F%21220x150r%2Fstrip%2Fgravity%2FCenter%2Fcrop%2F%21220x150%2Fquality%2F90",
        "title":"西北偏西，一些话和一份自驾摄影攻略",
        "content":"这篇游记共7523文字，125图片，阅读约需10分钟。 「正文」先说一些话。 如果你在城市呆久了，你会忘记这个世界本来的模样。 这句话曾无数次在我的脑海里浮现，特别是最近。想想从一月份疫情...",
        "city":"海西",
        "head":"http://p1-q.mafengwo.net/s10/M00/FC/75/wKgBZ1k0xpGAVtXIABDSK_WlQaM10.jpeg?imageMogr2%2Fthumbnail%2F%2116x16r%2Fgravity%2FCenter%2Fcrop%2F%2116x16%2Fquality%2F90",
        "name":"山峰不会写游记",
        "num":"688/98",
        "bing":"205",
        "app":""
    },
    {
        "id":"1",
        "img":"http://p1-q.mafengwo.net/s16/M00/67/A8/CoUBUl75lq-AVGLvAAhscFRnKwM636.jpg?imageMogr2%2Fthumbnail%2F%21220x150r%2Fstrip%2Fgravity%2FCenter%2Fcrop%2F%21220x150%2Fquality%2F90",
        "title":"西北偏西，一些话和一份自驾摄影攻略",
        "content":"这篇游记共7523文字，125图片，阅读约需10分钟。 「正文」先说一些话。 如果你在城市呆久了，你会忘记这个世界本来的模样。 这句话曾无数次在我的脑海里浮现，特别是最近。想想从一月份疫情...",
        "city":"海西",
        "head":"http://p1-q.mafengwo.net/s10/M00/FC/75/wKgBZ1k0xpGAVtXIABDSK_WlQaM10.jpeg?imageMogr2%2Fthumbnail%2F%2116x16r%2Fgravity%2FCenter%2Fcrop%2F%2116x16%2Fquality%2F90",
        "name":"山峰不会写游记",
        "num":"688/98",
        "bing":"205",
        "app":"0"
    },
    {
        "id":"2",
        "img":"http://p1-q.mafengwo.net/s16/M00/44/8D/CoUBUl62RluATOaMAAiO5ANuNec565.jpg?imageMogr2%2Fthumbnail%2F%21220x150r%2Fstrip%2Fgravity%2FCenter%2Fcrop%2F%21220x150%2Fquality%2F90",
        "title":"马来西亚｜惬意在槟城，纵身一跃仙本那",
        "content":"/大马与我，二度重逢/ “ 马来西亚 是我一直很想要去的地方，想去 沙巴 潜水，想去 热浪岛 回味年少时的夏日么么茶，想去 槟城 与斑斓的壁画融为一体，想去 仙本那 看看这个被称做世界上最...",
        "city":"马来西亚",
        "head":"http://p1-q.mafengwo.net/s11/M00/AB/17/wKgBEFrrsyiACkPHAACDGDZe9zg23.jpeg?imageMogr2%2Fthumbnail%2F%2116x16r%2Fgravity%2FCenter%2Fcrop%2F%2116x16%2Fquality%2F90",
        "name":"段小湃湃",
        "num":"688/98",
        "bing":"205",
        "app":"0"
    },
    {
        "id":"3",
        "img":"http://b1-q.mafengwo.net/s16/M00/C5/E7/CoUBUl6cvWmAcddiAAeUydTNRkc669.jpg?imageMogr2%2Fthumbnail%2F%21220x150r%2Fstrip%2Fgravity%2FCenter%2Fcrop%2F%21220x150%2Fquality%2F90",
        "title":"日本·北海道 | 十二月的初冬，赴一场暖阳下的皑皑白雪",
        "content":"又是暖冬，未见雪飘。 对于生活在南方的我们，亲眼目睹这个世界变得银装素裹，雪，盖满了屋顶，空中，晶莹的雪花慢慢飘落。 这一切仿佛只是一场奢望。 别人说，冷，是因为听见了下雪的声音。...",
        "city":"北海道",
        "head":"http://n1-q.mafengwo.net/s9/M00/1E/4F/wKgBs1ZgavqAQZK0AABYAtXMbAM52.jpeg?imageMogr2%2Fthumbnail%2F%2116x16r%2Fgravity%2FCenter%2Fcrop%2F%2116x16%2Fquality%2F90",
        "name":"阳光男该张小凡",
        "num":"7498/42",
        "bing":"297",
        "app":"1"
    },
    {
        "id":"4",
        "img":"http://n1-q.mafengwo.net/s16/M00/E8/14/CoUBUl6WiCaAVgxrAAsQkW5HW1w859.jpg?imageMogr2%2Fthumbnail%2F%21220x150r%2Fstrip%2Fgravity%2FCenter%2Fcrop%2F%21220x150%2Fquality%2F90",
        "title":"消失的地平线上的“香巴拉”和“女儿国”——秋游香格里拉、...",
        "content":"在《消失的地平线》里，描绘了一个隐藏在 中国 西南部的净土乐园——那是一个充满祥和、宁静、永恒和神秘色彩的藏族生息之地。在那里，三条河流交汇在一起，群山高耸入云，山顶白雪皑皑，脚...",
        "city":"香格里拉",
        "head":"http://n1-q.mafengwo.net/s7/M00/20/44/wKgB6lP7Iv-AICZKAAEIh2Copbc10.jpeg?imageMogr2%2Fthumbnail%2F%2116x16r%2Fgravity%2FCenter%2Fcrop%2F%2116x16%2Fquality%2F90",
        "name":"Jerry",
        "num":" 9644/86",
        "bing":"520",
        "app":"0"
    },
    {
        "id":"5",
        "img":"http://n1-q.mafengwo.net/s16/M00/CB/4F/CoUBUl6ItrKAd1b5ABnBmFWkEXA194.JPG?imageMogr2%2Fthumbnail%2F%21220x150r%2Fstrip%2Fgravity%2FCenter%2Fcrop%2F%21220x150%2Fquality%2F90",
        "title":"花见三城：京都、奈良、名古屋的26处樱花印象",
        "content":"三分至满开，留下樱吹雪的残念 很久之前便听闻 日本 关西 樱花的盛名，是“一生必赏一次的绝景”。 于是在清明时节，我来到 日本 关西 。八天时间，在 名古屋 、 京都 、 奈良 三城间辗转往...",
        "city":"京都",
        "head":"http://b1-q.mafengwo.net/s13/M00/09/AD/wKgEaVy3ziiAZkmFAACxxUhWHsc44.jpeg?imageMogr2%2Fthumbnail%2F%2116x16r%2Fgravity%2FCenter%2Fcrop%2F%2116x16%2Fquality%2F90",
        "name":"sockmai",
        "num":" 6076/29",
        "bing":"2349",
        "app":"0"
    },
    {
        "id":"6",
        "img":"http://n1-q.mafengwo.net/s16/M00/E4/E9/CoUBUl6Yc2uAZn57AA0qLpq18N8333.jpg?imageMogr2%2Fthumbnail%2F%21220x150r%2Fstrip%2Fgravity%2FCenter%2Fcrop%2F%21220x150%2Fquality%2F90",
        "title":"盛夏七月，一次中东之约,一场应许之旅",
        "content":"前言 以色列 和 约旦 ， 中东 文化中的明珠，历史文明古国、宗教圣地，没有太多的犹豫，今年的旅行地图锁定在了 中东 准备这一场旅行真的耗费了我大量的日日夜夜，为了行程、为了住宿、为了...",
        "city":"以色列",
        "head":"http://p1-q.mafengwo.net/s16/M00/57/2F/CoUBUl6jvBmAL00tABhW48I5aEY74.jpeg?imageMogr2%2Fthumbnail%2F%2116x16r%2Fgravity%2FCenter%2Fcrop%2F%2116x16%2Fquality%2F90",
        "name":"大香芋",
        "num":" 6543/62",
        "bing":"349",
        "app":"0"
    },
    {
        "id":"7",
        "img":"http://b1-q.mafengwo.net/s16/M00/89/31/CoUBUl6VW2WALqr1AAFuFHIwu6k72.jpeg?imageMogr2%2Fthumbnail%2F%21220x150r%2Fstrip%2Fgravity%2FCenter%2Fcrop%2F%21220x150%2Fquality%2F90",
        "title":"上帝的眼泪，锡兰微笑，这是我不能忘记的斯里兰卡（13天行程...",
        "content":"第六天，努沃埃利耶，从茶厂到粉红邮局 洛奇奇茶厂，兰卡最受欢迎的茶厂 对于喜欢喝茶的人来说， 斯里兰卡 的红茶可是一个很大的诱惑，谁都知道，锡兰红茶世界闻名，谁都想亲口品尝一下。所...",
        "city":"斯里兰卡",
        "head":"http://b1-q.mafengwo.net/s15/M00/6D/84/CoUBGV4n7YOAG2LwAABHT5LFfp020.jpeg?imageMogr2%2Fthumbnail%2F%2116x16r%2Fgravity%2FCenter%2Fcrop%2F%2116x16%2Fquality%2F90",
        "name":" 郝地瓜Cynthia",
        "num":"5675/24",
        "bing":"234",
        "app":"0"
    },
    {
        "id":"8",
        "img":"http://p1-q.mafengwo.net/s16/M00/08/B4/CoUBUl6VcYCAUwTTAAwMaS--fKc18.jpeg?imageMogr2%2Fthumbnail%2F%21220x150r%2Fstrip%2Fgravity%2FCenter%2Fcrop%2F%21220x150%2Fquality%2F90",
        "title":"日本漫游Day5 | 教练我想去镰仓",
        "content":"湘南海岸边的小城 说起 镰仓 ，你会想起什么呢？许多爱看动漫的年青人对 镰仓 的最初了解，应该来自于《灌篮高手》中的那经典一幕：海边的 镰仓 高校前站。对于陶醉在《 镰仓 物语》那文艺...",
        "city":"镰仓",
        "head":"http://n1-q.mafengwo.net/s15/M00/C3/12/CoUBGV4M8EWAU9RLAAC3ZLKaH8E32.jpeg?imageMogr2%2Fthumbnail%2F%2116x16r%2Fgravity%2FCenter%2Fcrop%2F%2116x16%2Fquality%2F90",
        "name":"行者",
        "num":"5856/20",
        "bing":"220",
        "app":"0"
    },
    {
        "id":"9",
        "img":"http://b1-q.mafengwo.net/s16/M00/DB/98/CoUBUl6NsEaAD8pFAAxZ3lQ5K1k547.jpg?imageMogr2%2Fthumbnail%2F%21220x150r%2Fstrip%2Fgravity%2FCenter%2Fcrop%2F%21220x150%2Fquality%2F90",
        "title":"#不止于春#去齐鲁，还一场春债（山东济南/济宁/泰安/聊城/日...",
        "content":"你说 胭脂用尽时，桃花就开了。 如今 夭桃满山谷，春风渡齐鲁。 于这孔孟之乡、礼仪之邦， 种下惠风和煦，栽下杏雨梨云。 从此 翠袖围香，绛绡落雪，芳息入骨， 惹来一身偿还不掉的春债。 济...",
        "city":"泰安",
        "head":"http://b1-q.mafengwo.net/s15/M00/E7/0F/CoUBGV4FlPmABPcpAABNJgFDHVI66.jpeg?imageMogr2%2Fthumbnail%2F%2116x16r%2Fgravity%2FCenter%2Fcrop%2F%2116x16%2Fquality%2F90",
        "name":"Drizzle细雨",
        "num":"9824/68",
        "bing":"515",
        "app":"0"
    },
    {
        "id":"10",
        "img":"http://p1-q.mafengwo.net/s16/M00/1C/5F/CoUBUl6K6kCAGWTlAAtskdwHOlM966.jpg?imageMogr2%2Fthumbnail%2F%21220x150r%2Fstrip%2Fgravity%2FCenter%2Fcrop%2F%21220x150%2Fquality%2F90",
        "title":"【东京—镰仓—高松—小豆岛—直岛—丰岛】东京的大雨，镰仓...",
        "content":"“快乐啊， 有时候不是大笑， 不是跟你笑着拥抱， 而是你看着他， 他看着你， 然后你们不知不觉的就笑了” 写在开篇 第三次去 日本 ，在 东京 和高松、 东京 和 屋久岛 的行程中犹豫了很久...",
        "city":"日本",
        "head":"http://b1-q.mafengwo.net/s16/M00/20/09/CoUBUl6K7V6AYpEqAAEE0xAOP6E52.jpeg?imageMogr2%2Fthumbnail%2F%2116x16r%2Fgravity%2FCenter%2Fcrop%2F%2116x16%2Fquality%2F90",
        "name":"嘉errr",
        "num":"9860/19",
        "bing":"340",
        "app":"0"
    },
    {
        "id":"11",
        "img":"http://p1-q.mafengwo.net/s16/M00/D4/B4/CoUBUl6YZrCAbtPNAA2aYXj0vc4603.jpg?imageMogr2%2Fthumbnail%2F%21220x150r%2Fstrip%2Fgravity%2FCenter%2Fcrop%2F%21220x150%2Fquality%2F90",
        "title":"一篇迟到五年的游记 | 台湾环岛八日全记录",
        "content":"intro 说起 台湾 最初的记忆是小时候听到的那些流行歌曲 某某歌星是 台湾 的 小时候只知道 台湾 这么一个地方 因为以前条件限制 获取资讯只能通过电视 或者音乐影视这些媒介 对 台湾 的了解...",
        "city":"台湾",
        "head":"http://b1-q.mafengwo.net/s10/M00/4C/FC/wKgBZ1j1y-SACwgKAAFX3v7cyoA06.jpeg?imageMogr2%2Fthumbnail%2F%2116x16r%2Fgravity%2FCenter%2Fcrop%2F%2116x16%2Fquality%2F90",
        "name":"1983",
        "num":" 3762/5",
        "bing":"264",
        "app":"0"
    },
    {
        "id":"12",
        "img":"http://p1-q.mafengwo.net/s16/M00/67/A8/CoUBUl75lq-AVGLvAAhscFRnKwM636.jpg?imageMogr2%2Fthumbnail%2F%21220x150r%2Fstrip%2Fgravity%2FCenter%2Fcrop%2F%21220x150%2Fquality%2F90",
        "title":"西北偏西，一些话和一份自驾摄影攻略",
        "content":"这篇游记共7523文字，125图片，阅读约需10分钟。 「正文」先说一些话。 如果你在城市呆久了，你会忘记这个世界本来的模样。 这句话曾无数次在我的脑海里浮现，特别是最近。想想从一月份疫情...",
        "city":"海西",
        "head":"http://p1-q.mafengwo.net/s10/M00/FC/75/wKgBZ1k0xpGAVtXIABDSK_WlQaM10.jpeg?imageMogr2%2Fthumbnail%2F%2116x16r%2Fgravity%2FCenter%2Fcrop%2F%2116x16%2Fquality%2F90",
        "name":"山峰不会写游记",
        "num":"688/98",
        "bing":"205",
        "app":""
    },
    {
        "id":"1",
        "img":"http://p1-q.mafengwo.net/s16/M00/67/A8/CoUBUl75lq-AVGLvAAhscFRnKwM636.jpg?imageMogr2%2Fthumbnail%2F%21220x150r%2Fstrip%2Fgravity%2FCenter%2Fcrop%2F%21220x150%2Fquality%2F90",
        "title":"西北偏西，一些话和一份自驾摄影攻略",
        "content":"这篇游记共7523文字，125图片，阅读约需10分钟。 「正文」先说一些话。 如果你在城市呆久了，你会忘记这个世界本来的模样。 这句话曾无数次在我的脑海里浮现，特别是最近。想想从一月份疫情...",
        "city":"海西",
        "head":"http://p1-q.mafengwo.net/s10/M00/FC/75/wKgBZ1k0xpGAVtXIABDSK_WlQaM10.jpeg?imageMogr2%2Fthumbnail%2F%2116x16r%2Fgravity%2FCenter%2Fcrop%2F%2116x16%2Fquality%2F90",
        "name":"山峰不会写游记",
        "num":"688/98",
        "bing":"205",
        "app":"0"
    },
    {
        "id":"2",
        "img":"http://p1-q.mafengwo.net/s16/M00/44/8D/CoUBUl62RluATOaMAAiO5ANuNec565.jpg?imageMogr2%2Fthumbnail%2F%21220x150r%2Fstrip%2Fgravity%2FCenter%2Fcrop%2F%21220x150%2Fquality%2F90",
        "title":"马来西亚｜惬意在槟城，纵身一跃仙本那",
        "content":"/大马与我，二度重逢/ “ 马来西亚 是我一直很想要去的地方，想去 沙巴 潜水，想去 热浪岛 回味年少时的夏日么么茶，想去 槟城 与斑斓的壁画融为一体，想去 仙本那 看看这个被称做世界上最...",
        "city":"马来西亚",
        "head":"http://p1-q.mafengwo.net/s11/M00/AB/17/wKgBEFrrsyiACkPHAACDGDZe9zg23.jpeg?imageMogr2%2Fthumbnail%2F%2116x16r%2Fgravity%2FCenter%2Fcrop%2F%2116x16%2Fquality%2F90",
        "name":"段小湃湃",
        "num":"688/98",
        "bing":"205",
        "app":"0"
    },
    {
        "id":"3",
        "img":"http://b1-q.mafengwo.net/s16/M00/C5/E7/CoUBUl6cvWmAcddiAAeUydTNRkc669.jpg?imageMogr2%2Fthumbnail%2F%21220x150r%2Fstrip%2Fgravity%2FCenter%2Fcrop%2F%21220x150%2Fquality%2F90",
        "title":"日本·北海道 | 十二月的初冬，赴一场暖阳下的皑皑白雪",
        "content":"又是暖冬，未见雪飘。 对于生活在南方的我们，亲眼目睹这个世界变得银装素裹，雪，盖满了屋顶，空中，晶莹的雪花慢慢飘落。 这一切仿佛只是一场奢望。 别人说，冷，是因为听见了下雪的声音。...",
        "city":"北海道",
        "head":"http://n1-q.mafengwo.net/s9/M00/1E/4F/wKgBs1ZgavqAQZK0AABYAtXMbAM52.jpeg?imageMogr2%2Fthumbnail%2F%2116x16r%2Fgravity%2FCenter%2Fcrop%2F%2116x16%2Fquality%2F90",
        "name":"阳光男该张小凡",
        "num":"7498/42",
        "bing":"297",
        "app":"1"
    },
    {
        "id":"4",
        "img":"http://n1-q.mafengwo.net/s16/M00/E8/14/CoUBUl6WiCaAVgxrAAsQkW5HW1w859.jpg?imageMogr2%2Fthumbnail%2F%21220x150r%2Fstrip%2Fgravity%2FCenter%2Fcrop%2F%21220x150%2Fquality%2F90",
        "title":"消失的地平线上的“香巴拉”和“女儿国”——秋游香格里拉、...",
        "content":"在《消失的地平线》里，描绘了一个隐藏在 中国 西南部的净土乐园——那是一个充满祥和、宁静、永恒和神秘色彩的藏族生息之地。在那里，三条河流交汇在一起，群山高耸入云，山顶白雪皑皑，脚...",
        "city":"香格里拉",
        "head":"http://n1-q.mafengwo.net/s7/M00/20/44/wKgB6lP7Iv-AICZKAAEIh2Copbc10.jpeg?imageMogr2%2Fthumbnail%2F%2116x16r%2Fgravity%2FCenter%2Fcrop%2F%2116x16%2Fquality%2F90",
        "name":"Jerry",
        "num":" 9644/86",
        "bing":"520",
        "app":"0"
    },
    {
        "id":"5",
        "img":"http://n1-q.mafengwo.net/s16/M00/CB/4F/CoUBUl6ItrKAd1b5ABnBmFWkEXA194.JPG?imageMogr2%2Fthumbnail%2F%21220x150r%2Fstrip%2Fgravity%2FCenter%2Fcrop%2F%21220x150%2Fquality%2F90",
        "title":"花见三城：京都、奈良、名古屋的26处樱花印象",
        "content":"三分至满开，留下樱吹雪的残念 很久之前便听闻 日本 关西 樱花的盛名，是“一生必赏一次的绝景”。 于是在清明时节，我来到 日本 关西 。八天时间，在 名古屋 、 京都 、 奈良 三城间辗转往...",
        "city":"京都",
        "head":"http://b1-q.mafengwo.net/s13/M00/09/AD/wKgEaVy3ziiAZkmFAACxxUhWHsc44.jpeg?imageMogr2%2Fthumbnail%2F%2116x16r%2Fgravity%2FCenter%2Fcrop%2F%2116x16%2Fquality%2F90",
        "name":"sockmai",
        "num":" 6076/29",
        "bing":"2349",
        "app":"0"
    },
    {
        "id":"6",
        "img":"http://n1-q.mafengwo.net/s16/M00/E4/E9/CoUBUl6Yc2uAZn57AA0qLpq18N8333.jpg?imageMogr2%2Fthumbnail%2F%21220x150r%2Fstrip%2Fgravity%2FCenter%2Fcrop%2F%21220x150%2Fquality%2F90",
        "title":"盛夏七月，一次中东之约,一场应许之旅",
        "content":"前言 以色列 和 约旦 ， 中东 文化中的明珠，历史文明古国、宗教圣地，没有太多的犹豫，今年的旅行地图锁定在了 中东 准备这一场旅行真的耗费了我大量的日日夜夜，为了行程、为了住宿、为了...",
        "city":"以色列",
        "head":"http://p1-q.mafengwo.net/s16/M00/57/2F/CoUBUl6jvBmAL00tABhW48I5aEY74.jpeg?imageMogr2%2Fthumbnail%2F%2116x16r%2Fgravity%2FCenter%2Fcrop%2F%2116x16%2Fquality%2F90",
        "name":"大香芋",
        "num":" 6543/62",
        "bing":"349",
        "app":"0"
    },
    {
        "id":"7",
        "img":"http://b1-q.mafengwo.net/s16/M00/89/31/CoUBUl6VW2WALqr1AAFuFHIwu6k72.jpeg?imageMogr2%2Fthumbnail%2F%21220x150r%2Fstrip%2Fgravity%2FCenter%2Fcrop%2F%21220x150%2Fquality%2F90",
        "title":"上帝的眼泪，锡兰微笑，这是我不能忘记的斯里兰卡（13天行程...",
        "content":"第六天，努沃埃利耶，从茶厂到粉红邮局 洛奇奇茶厂，兰卡最受欢迎的茶厂 对于喜欢喝茶的人来说， 斯里兰卡 的红茶可是一个很大的诱惑，谁都知道，锡兰红茶世界闻名，谁都想亲口品尝一下。所...",
        "city":"斯里兰卡",
        "head":"http://b1-q.mafengwo.net/s15/M00/6D/84/CoUBGV4n7YOAG2LwAABHT5LFfp020.jpeg?imageMogr2%2Fthumbnail%2F%2116x16r%2Fgravity%2FCenter%2Fcrop%2F%2116x16%2Fquality%2F90",
        "name":" 郝地瓜Cynthia",
        "num":"5675/24",
        "bing":"234",
        "app":"0"
    },
    {
        "id":"8",
        "img":"http://p1-q.mafengwo.net/s16/M00/08/B4/CoUBUl6VcYCAUwTTAAwMaS--fKc18.jpeg?imageMogr2%2Fthumbnail%2F%21220x150r%2Fstrip%2Fgravity%2FCenter%2Fcrop%2F%21220x150%2Fquality%2F90",
        "title":"日本漫游Day5 | 教练我想去镰仓",
        "content":"湘南海岸边的小城 说起 镰仓 ，你会想起什么呢？许多爱看动漫的年青人对 镰仓 的最初了解，应该来自于《灌篮高手》中的那经典一幕：海边的 镰仓 高校前站。对于陶醉在《 镰仓 物语》那文艺...",
        "city":"镰仓",
        "head":"http://n1-q.mafengwo.net/s15/M00/C3/12/CoUBGV4M8EWAU9RLAAC3ZLKaH8E32.jpeg?imageMogr2%2Fthumbnail%2F%2116x16r%2Fgravity%2FCenter%2Fcrop%2F%2116x16%2Fquality%2F90",
        "name":"行者",
        "num":"5856/20",
        "bing":"220",
        "app":"0"
    },
    {
        "id":"9",
        "img":"http://b1-q.mafengwo.net/s16/M00/DB/98/CoUBUl6NsEaAD8pFAAxZ3lQ5K1k547.jpg?imageMogr2%2Fthumbnail%2F%21220x150r%2Fstrip%2Fgravity%2FCenter%2Fcrop%2F%21220x150%2Fquality%2F90",
        "title":"#不止于春#去齐鲁，还一场春债（山东济南/济宁/泰安/聊城/日...",
        "content":"你说 胭脂用尽时，桃花就开了。 如今 夭桃满山谷，春风渡齐鲁。 于这孔孟之乡、礼仪之邦， 种下惠风和煦，栽下杏雨梨云。 从此 翠袖围香，绛绡落雪，芳息入骨， 惹来一身偿还不掉的春债。 济...",
        "city":"泰安",
        "head":"http://b1-q.mafengwo.net/s15/M00/E7/0F/CoUBGV4FlPmABPcpAABNJgFDHVI66.jpeg?imageMogr2%2Fthumbnail%2F%2116x16r%2Fgravity%2FCenter%2Fcrop%2F%2116x16%2Fquality%2F90",
        "name":"Drizzle细雨",
        "num":"9824/68",
        "bing":"515",
        "app":"0"
    },
    {
        "id":"10",
        "img":"http://p1-q.mafengwo.net/s16/M00/1C/5F/CoUBUl6K6kCAGWTlAAtskdwHOlM966.jpg?imageMogr2%2Fthumbnail%2F%21220x150r%2Fstrip%2Fgravity%2FCenter%2Fcrop%2F%21220x150%2Fquality%2F90",
        "title":"【东京—镰仓—高松—小豆岛—直岛—丰岛】东京的大雨，镰仓...",
        "content":"“快乐啊， 有时候不是大笑， 不是跟你笑着拥抱， 而是你看着他， 他看着你， 然后你们不知不觉的就笑了” 写在开篇 第三次去 日本 ，在 东京 和高松、 东京 和 屋久岛 的行程中犹豫了很久...",
        "city":"日本",
        "head":"http://b1-q.mafengwo.net/s16/M00/20/09/CoUBUl6K7V6AYpEqAAEE0xAOP6E52.jpeg?imageMogr2%2Fthumbnail%2F%2116x16r%2Fgravity%2FCenter%2Fcrop%2F%2116x16%2Fquality%2F90",
        "name":"嘉errr",
        "num":"9860/19",
        "bing":"340",
        "app":"0"
    },
    {
        "id":"11",
        "img":"http://p1-q.mafengwo.net/s16/M00/D4/B4/CoUBUl6YZrCAbtPNAA2aYXj0vc4603.jpg?imageMogr2%2Fthumbnail%2F%21220x150r%2Fstrip%2Fgravity%2FCenter%2Fcrop%2F%21220x150%2Fquality%2F90",
        "title":"一篇迟到五年的游记 | 台湾环岛八日全记录",
        "content":"intro 说起 台湾 最初的记忆是小时候听到的那些流行歌曲 某某歌星是 台湾 的 小时候只知道 台湾 这么一个地方 因为以前条件限制 获取资讯只能通过电视 或者音乐影视这些媒介 对 台湾 的了解...",
        "city":"台湾",
        "head":"http://b1-q.mafengwo.net/s10/M00/4C/FC/wKgBZ1j1y-SACwgKAAFX3v7cyoA06.jpeg?imageMogr2%2Fthumbnail%2F%2116x16r%2Fgravity%2FCenter%2Fcrop%2F%2116x16%2Fquality%2F90",
        "name":"1983",
        "num":" 3762/5",
        "bing":"264",
        "app":"0"
    },
    {
        "id":"12",
        "img":"http://p1-q.mafengwo.net/s16/M00/67/A8/CoUBUl75lq-AVGLvAAhscFRnKwM636.jpg?imageMogr2%2Fthumbnail%2F%21220x150r%2Fstrip%2Fgravity%2FCenter%2Fcrop%2F%21220x150%2Fquality%2F90",
        "title":"西北偏西，一些话和一份自驾摄影攻略",
        "content":"这篇游记共7523文字，125图片，阅读约需10分钟。 「正文」先说一些话。 如果你在城市呆久了，你会忘记这个世界本来的模样。 这句话曾无数次在我的脑海里浮现，特别是最近。想想从一月份疫情...",
        "city":"海西",
        "head":"http://p1-q.mafengwo.net/s10/M00/FC/75/wKgBZ1k0xpGAVtXIABDSK_WlQaM10.jpeg?imageMogr2%2Fthumbnail%2F%2116x16r%2Fgravity%2FCenter%2Fcrop%2F%2116x16%2Fquality%2F90",
        "name":"山峰不会写游记",
        "num":"688/98",
        "bing":"205",
        "app":""
    },
    {
        "id":"1",
        "img":"http://p1-q.mafengwo.net/s16/M00/67/A8/CoUBUl75lq-AVGLvAAhscFRnKwM636.jpg?imageMogr2%2Fthumbnail%2F%21220x150r%2Fstrip%2Fgravity%2FCenter%2Fcrop%2F%21220x150%2Fquality%2F90",
        "title":"西北偏西，一些话和一份自驾摄影攻略",
        "content":"这篇游记共7523文字，125图片，阅读约需10分钟。 「正文」先说一些话。 如果你在城市呆久了，你会忘记这个世界本来的模样。 这句话曾无数次在我的脑海里浮现，特别是最近。想想从一月份疫情...",
        "city":"海西",
        "head":"http://p1-q.mafengwo.net/s10/M00/FC/75/wKgBZ1k0xpGAVtXIABDSK_WlQaM10.jpeg?imageMogr2%2Fthumbnail%2F%2116x16r%2Fgravity%2FCenter%2Fcrop%2F%2116x16%2Fquality%2F90",
        "name":"山峰不会写游记",
        "num":"688/98",
        "bing":"205",
        "app":"0"
    },
    {
        "id":"2",
        "img":"http://p1-q.mafengwo.net/s16/M00/44/8D/CoUBUl62RluATOaMAAiO5ANuNec565.jpg?imageMogr2%2Fthumbnail%2F%21220x150r%2Fstrip%2Fgravity%2FCenter%2Fcrop%2F%21220x150%2Fquality%2F90",
        "title":"马来西亚｜惬意在槟城，纵身一跃仙本那",
        "content":"/大马与我，二度重逢/ “ 马来西亚 是我一直很想要去的地方，想去 沙巴 潜水，想去 热浪岛 回味年少时的夏日么么茶，想去 槟城 与斑斓的壁画融为一体，想去 仙本那 看看这个被称做世界上最...",
        "city":"马来西亚",
        "head":"http://p1-q.mafengwo.net/s11/M00/AB/17/wKgBEFrrsyiACkPHAACDGDZe9zg23.jpeg?imageMogr2%2Fthumbnail%2F%2116x16r%2Fgravity%2FCenter%2Fcrop%2F%2116x16%2Fquality%2F90",
        "name":"段小湃湃",
        "num":"688/98",
        "bing":"205",
        "app":"0"
    },
    {
        "id":"3",
        "img":"http://b1-q.mafengwo.net/s16/M00/C5/E7/CoUBUl6cvWmAcddiAAeUydTNRkc669.jpg?imageMogr2%2Fthumbnail%2F%21220x150r%2Fstrip%2Fgravity%2FCenter%2Fcrop%2F%21220x150%2Fquality%2F90",
        "title":"日本·北海道 | 十二月的初冬，赴一场暖阳下的皑皑白雪",
        "content":"又是暖冬，未见雪飘。 对于生活在南方的我们，亲眼目睹这个世界变得银装素裹，雪，盖满了屋顶，空中，晶莹的雪花慢慢飘落。 这一切仿佛只是一场奢望。 别人说，冷，是因为听见了下雪的声音。...",
        "city":"北海道",
        "head":"http://n1-q.mafengwo.net/s9/M00/1E/4F/wKgBs1ZgavqAQZK0AABYAtXMbAM52.jpeg?imageMogr2%2Fthumbnail%2F%2116x16r%2Fgravity%2FCenter%2Fcrop%2F%2116x16%2Fquality%2F90",
        "name":"阳光男该张小凡",
        "num":"7498/42",
        "bing":"297",
        "app":"1"
    },
    {
        "id":"4",
        "img":"http://n1-q.mafengwo.net/s16/M00/E8/14/CoUBUl6WiCaAVgxrAAsQkW5HW1w859.jpg?imageMogr2%2Fthumbnail%2F%21220x150r%2Fstrip%2Fgravity%2FCenter%2Fcrop%2F%21220x150%2Fquality%2F90",
        "title":"消失的地平线上的“香巴拉”和“女儿国”——秋游香格里拉、...",
        "content":"在《消失的地平线》里，描绘了一个隐藏在 中国 西南部的净土乐园——那是一个充满祥和、宁静、永恒和神秘色彩的藏族生息之地。在那里，三条河流交汇在一起，群山高耸入云，山顶白雪皑皑，脚...",
        "city":"香格里拉",
        "head":"http://n1-q.mafengwo.net/s7/M00/20/44/wKgB6lP7Iv-AICZKAAEIh2Copbc10.jpeg?imageMogr2%2Fthumbnail%2F%2116x16r%2Fgravity%2FCenter%2Fcrop%2F%2116x16%2Fquality%2F90",
        "name":"Jerry",
        "num":" 9644/86",
        "bing":"520",
        "app":"0"
    },
    {
        "id":"5",
        "img":"http://n1-q.mafengwo.net/s16/M00/CB/4F/CoUBUl6ItrKAd1b5ABnBmFWkEXA194.JPG?imageMogr2%2Fthumbnail%2F%21220x150r%2Fstrip%2Fgravity%2FCenter%2Fcrop%2F%21220x150%2Fquality%2F90",
        "title":"花见三城：京都、奈良、名古屋的26处樱花印象",
        "content":"三分至满开，留下樱吹雪的残念 很久之前便听闻 日本 关西 樱花的盛名，是“一生必赏一次的绝景”。 于是在清明时节，我来到 日本 关西 。八天时间，在 名古屋 、 京都 、 奈良 三城间辗转往...",
        "city":"京都",
        "head":"http://b1-q.mafengwo.net/s13/M00/09/AD/wKgEaVy3ziiAZkmFAACxxUhWHsc44.jpeg?imageMogr2%2Fthumbnail%2F%2116x16r%2Fgravity%2FCenter%2Fcrop%2F%2116x16%2Fquality%2F90",
        "name":"sockmai",
        "num":" 6076/29",
        "bing":"2349",
        "app":"0"
    },
    {
        "id":"6",
        "img":"http://n1-q.mafengwo.net/s16/M00/E4/E9/CoUBUl6Yc2uAZn57AA0qLpq18N8333.jpg?imageMogr2%2Fthumbnail%2F%21220x150r%2Fstrip%2Fgravity%2FCenter%2Fcrop%2F%21220x150%2Fquality%2F90",
        "title":"盛夏七月，一次中东之约,一场应许之旅",
        "content":"前言 以色列 和 约旦 ， 中东 文化中的明珠，历史文明古国、宗教圣地，没有太多的犹豫，今年的旅行地图锁定在了 中东 准备这一场旅行真的耗费了我大量的日日夜夜，为了行程、为了住宿、为了...",
        "city":"以色列",
        "head":"http://p1-q.mafengwo.net/s16/M00/57/2F/CoUBUl6jvBmAL00tABhW48I5aEY74.jpeg?imageMogr2%2Fthumbnail%2F%2116x16r%2Fgravity%2FCenter%2Fcrop%2F%2116x16%2Fquality%2F90",
        "name":"大香芋",
        "num":" 6543/62",
        "bing":"349",
        "app":"0"
    },
    {
        "id":"7",
        "img":"http://b1-q.mafengwo.net/s16/M00/89/31/CoUBUl6VW2WALqr1AAFuFHIwu6k72.jpeg?imageMogr2%2Fthumbnail%2F%21220x150r%2Fstrip%2Fgravity%2FCenter%2Fcrop%2F%21220x150%2Fquality%2F90",
        "title":"上帝的眼泪，锡兰微笑，这是我不能忘记的斯里兰卡（13天行程...",
        "content":"第六天，努沃埃利耶，从茶厂到粉红邮局 洛奇奇茶厂，兰卡最受欢迎的茶厂 对于喜欢喝茶的人来说， 斯里兰卡 的红茶可是一个很大的诱惑，谁都知道，锡兰红茶世界闻名，谁都想亲口品尝一下。所...",
        "city":"斯里兰卡",
        "head":"http://b1-q.mafengwo.net/s15/M00/6D/84/CoUBGV4n7YOAG2LwAABHT5LFfp020.jpeg?imageMogr2%2Fthumbnail%2F%2116x16r%2Fgravity%2FCenter%2Fcrop%2F%2116x16%2Fquality%2F90",
        "name":" 郝地瓜Cynthia",
        "num":"5675/24",
        "bing":"234",
        "app":"0"
    },
    {
        "id":"8",
        "img":"http://p1-q.mafengwo.net/s16/M00/08/B4/CoUBUl6VcYCAUwTTAAwMaS--fKc18.jpeg?imageMogr2%2Fthumbnail%2F%21220x150r%2Fstrip%2Fgravity%2FCenter%2Fcrop%2F%21220x150%2Fquality%2F90",
        "title":"日本漫游Day5 | 教练我想去镰仓",
        "content":"湘南海岸边的小城 说起 镰仓 ，你会想起什么呢？许多爱看动漫的年青人对 镰仓 的最初了解，应该来自于《灌篮高手》中的那经典一幕：海边的 镰仓 高校前站。对于陶醉在《 镰仓 物语》那文艺...",
        "city":"镰仓",
        "head":"http://n1-q.mafengwo.net/s15/M00/C3/12/CoUBGV4M8EWAU9RLAAC3ZLKaH8E32.jpeg?imageMogr2%2Fthumbnail%2F%2116x16r%2Fgravity%2FCenter%2Fcrop%2F%2116x16%2Fquality%2F90",
        "name":"行者",
        "num":"5856/20",
        "bing":"220",
        "app":"0"
    },
    {
        "id":"9",
        "img":"http://b1-q.mafengwo.net/s16/M00/DB/98/CoUBUl6NsEaAD8pFAAxZ3lQ5K1k547.jpg?imageMogr2%2Fthumbnail%2F%21220x150r%2Fstrip%2Fgravity%2FCenter%2Fcrop%2F%21220x150%2Fquality%2F90",
        "title":"#不止于春#去齐鲁，还一场春债（山东济南/济宁/泰安/聊城/日...",
        "content":"你说 胭脂用尽时，桃花就开了。 如今 夭桃满山谷，春风渡齐鲁。 于这孔孟之乡、礼仪之邦， 种下惠风和煦，栽下杏雨梨云。 从此 翠袖围香，绛绡落雪，芳息入骨， 惹来一身偿还不掉的春债。 济...",
        "city":"泰安",
        "head":"http://b1-q.mafengwo.net/s15/M00/E7/0F/CoUBGV4FlPmABPcpAABNJgFDHVI66.jpeg?imageMogr2%2Fthumbnail%2F%2116x16r%2Fgravity%2FCenter%2Fcrop%2F%2116x16%2Fquality%2F90",
        "name":"Drizzle细雨",
        "num":"9824/68",
        "bing":"515",
        "app":"0"
    },
    {
        "id":"10",
        "img":"http://p1-q.mafengwo.net/s16/M00/1C/5F/CoUBUl6K6kCAGWTlAAtskdwHOlM966.jpg?imageMogr2%2Fthumbnail%2F%21220x150r%2Fstrip%2Fgravity%2FCenter%2Fcrop%2F%21220x150%2Fquality%2F90",
        "title":"【东京—镰仓—高松—小豆岛—直岛—丰岛】东京的大雨，镰仓...",
        "content":"“快乐啊， 有时候不是大笑， 不是跟你笑着拥抱， 而是你看着他， 他看着你， 然后你们不知不觉的就笑了” 写在开篇 第三次去 日本 ，在 东京 和高松、 东京 和 屋久岛 的行程中犹豫了很久...",
        "city":"日本",
        "head":"http://b1-q.mafengwo.net/s16/M00/20/09/CoUBUl6K7V6AYpEqAAEE0xAOP6E52.jpeg?imageMogr2%2Fthumbnail%2F%2116x16r%2Fgravity%2FCenter%2Fcrop%2F%2116x16%2Fquality%2F90",
        "name":"嘉errr",
        "num":"9860/19",
        "bing":"340",
        "app":"0"
    },
    {
        "id":"11",
        "img":"http://p1-q.mafengwo.net/s16/M00/D4/B4/CoUBUl6YZrCAbtPNAA2aYXj0vc4603.jpg?imageMogr2%2Fthumbnail%2F%21220x150r%2Fstrip%2Fgravity%2FCenter%2Fcrop%2F%21220x150%2Fquality%2F90",
        "title":"一篇迟到五年的游记 | 台湾环岛八日全记录",
        "content":"intro 说起 台湾 最初的记忆是小时候听到的那些流行歌曲 某某歌星是 台湾 的 小时候只知道 台湾 这么一个地方 因为以前条件限制 获取资讯只能通过电视 或者音乐影视这些媒介 对 台湾 的了解...",
        "city":"台湾",
        "head":"http://b1-q.mafengwo.net/s10/M00/4C/FC/wKgBZ1j1y-SACwgKAAFX3v7cyoA06.jpeg?imageMogr2%2Fthumbnail%2F%2116x16r%2Fgravity%2FCenter%2Fcrop%2F%2116x16%2Fquality%2F90",
        "name":"1983",
        "num":" 3762/5",
        "bing":"264",
        "app":"0"
    },
    {
        "id":"12",
        "img":"http://p1-q.mafengwo.net/s16/M00/67/A8/CoUBUl75lq-AVGLvAAhscFRnKwM636.jpg?imageMogr2%2Fthumbnail%2F%21220x150r%2Fstrip%2Fgravity%2FCenter%2Fcrop%2F%21220x150%2Fquality%2F90",
        "title":"西北偏西，一些话和一份自驾摄影攻略",
        "content":"这篇游记共7523文字，125图片，阅读约需10分钟。 「正文」先说一些话。 如果你在城市呆久了，你会忘记这个世界本来的模样。 这句话曾无数次在我的脑海里浮现，特别是最近。想想从一月份疫情...",
        "city":"海西",
        "head":"http://p1-q.mafengwo.net/s10/M00/FC/75/wKgBZ1k0xpGAVtXIABDSK_WlQaM10.jpeg?imageMogr2%2Fthumbnail%2F%2116x16r%2Fgravity%2FCenter%2Fcrop%2F%2116x16%2Fquality%2F90",
        "name":"山峰不会写游记",
        "num":"688/98",
        "bing":"205",
        "app":""
    }
]